{
  "screen_template_id": "5f4c5802-746b-4125-9ed1-9432b4b015d5",
  "name": "buyer_entity_name",
  "state": "draft",
  "title": "What is the legal name of the entity?",
  "label": "Entity Name",
  "description": "If the entity is a trust, enter the complete trust name. If under probate, enter the full name of the estate, including the case number.",
  "stage": "final_details",
  "section": "buyers",
  "scope": {
    "buyer_entity": true
  },
  "tips": "Enter the complete legal name exactly as it appears on official documents.",
  "tip_links": {},
  "small_print": "Please ensure the name entered above exactly matches both the supporting documentation and how the entity name appears on the Secretary of State website of the state where the entity is registered. Discrepancies in the entity name may cause delays in closing.",
  "is_required": true,
  "is_private": false,
  "is_editable": true,
  "internal": {
    "references": "ENTITY-NAME-2024-001",
    "notes": "Legal name of buying entity"
  },
  "components": {
    "buyer_entity_name": {
      "id": "014345ec-5d75-4362-8a77-9ecf9d1c8b76",
      "component_type": "input_text_area",
      "name": "buyer_entity_name",
      "is_array": false,
      "is_private": false,
      "is_editable": true,
      "is_required": true,
      "is_visible": true,
      "value": null,
      "default_value": null,
      "suggested": {
        "value": "not_empty",
        "hint": "This field is required.",
        "warning": ""
      },
      "validation": {
        "value_type": "text",
        "min_length": 0,
        "max_length": 500,
        "required": false
      },
      "formatting": {
        "type": "text"
      },
      "tooltip": "Enter the legal name of the entity",
      "fields": [
        {
          "id": "89d18427-35a0-4968-aa90-19a10985c80d",
          "name": "placeholder",
          "label": null,
          "default_value": "Enter legal entity name",
          "validation": {
            "required": true
          },
          "formatting": {
            "type": "text",
            "is_placeholder": true
          }
        }
      ],
      "logic": [],
      "children": []
    }
  }
}